AUTHORS.markdown
HISTORY.markdown
LICENSE.txt
MANIFEST.in
README.markdown
TODO.markdown
setup.py
journal/__init__.py
journal/main.py
journal/parse.py
journal.egg-info/PKG-INFO
journal.egg-info/SOURCES.txt
journal.egg-info/dependency_links.txt
journal.egg-info/entry_points.txt
journal.egg-info/top_level.txt
tests/__init__.py
tests/test_date_parsing.py