Metadata-Version: 1.0
Name: journal
Version: 0.3.0
Summary: A CLI tool to help with keeping a work/personal journal
Home-page: https://github.com/askedrelic/journal
Author: Matt Behrens <askedrelic@gmail.com>
Author-email: askedrelic@gmail.com
License: Copyright (c) 2012 Matt Behrens <askedrelic@gmail.com>
